{
"identifier": "subst",
"sourceCodeText": "sr",
"PWatch": "PW",
"vItemType": "vI",
"fln": "fl",
"nxp": "np",
"isSystemVar": "by",
"anySleeping": "yz",
"statement": "mt",
"dbgprint": "DP",
"wakeTime": "tw",
"nextWake": "xw",
"cur": "cu",
"arg": "ag",
"WaitingCount": "wc",
"Cam": "cm",
"needWakeTime": "nw",
"pollCycles": "po",
"PisB": "Ps",
"Proj": "Pj",
"begv": "BV",
"assignFromSys": "AY",
"tkc": "tc",
"endv": "Ev",
"autoUnload": "au",
"iPropWatch": "ip",
"comp": "cm",
"VarNotifyWatchingFn": "NF",
"assignIndexInternal": "AI",
"TriggerWatch": "TW",
"NextPh": "NP",
"SConn": "Cn",
"v2vec": "ZV",
"v2InvItemFilter": "qw",
"sch": "ed",
"RunnableCount": "rs",
"iBlockWatch": "ib",
"MSta": "Sa",
"PropertyGetFn": "PG",
"PropertySetFn": "PS",
"fln2": "L2",
"retIndexWritable": "wr",
"killName": "kn",
"Scheduler": "Ed",
"Ref": "R",
"si1": "j1",
"vBoundingSphere": "vS",
"ReCountStates": "Re",
"args": "ar",
"nxi": "O",
"PropertyHandlerPair": "P",
"num": "X",
"sy": "y",
"Tokenizer": "J",
"ths": "F",
"Sen": "o",
"MSus": "q",
"SCtl": "E",
"vVec": "Z",
"word": "d",
"isn": "N",
"stk": "k",
"block": "bk",
"popv": "Q",
"StEl": "L",
"AverageCpuOverXFrames": "U",
"consoleName": "c",
"pushv": "I",
"tkr": "tr",
"mkv": "M",
"PhFns": "z",
"watches": "w",
"stCount": "C",
"propWatches": "p",
"assign": "ig",
"blockWatches": "bw",
"ret": "rt",
"am": "a",
"st": "u",
"th": "h",
"cx": "x",
"con": "co",
"si": "j",
"name": "nm",
"EnableDebugPrint": "D",
"BCX": "B",
"sourceName": "m",
"State": "A",
"Token": "K",
"Thread": "T",
"sub": "s",
"SysVar": "S",
"Var": "V"
}